composio_praisonai/__init__.py
composio_praisonai/toolset.py
composio_praisonai-0.7.20.dist-info/METADATA
composio_praisonai-0.7.20.dist-info/WHEEL
composio_praisonai-0.7.20.dist-info/top_level.txt
composio_praisonai-0.7.20.dist-info/RECORD
