Metadata-Version: 2.4
Name: composio_praisonai
Version: 0.7.20
Summary: Use Composio Tools to enhance your PraisonAI agents capabilities.
Home-page: https://github.com/ComposioHQ/composio
Author: Sawradip
Author-email: sawradip@composio.dev
Classifier: Programming Language :: Python :: 3
Classifier: License :: OSI Approved :: Apache Software License
Classifier: Operating System :: OS Independent
Requires-Python: >=3.9
Requires-Dist: composio_core<0.8.0,>=0.7.0
Requires-Dist: PraisonAI>=0.0.2
Dynamic: author
Dynamic: author-email
Dynamic: classifier
Dynamic: description
Dynamic: description-content-type
Dynamic: home-page
Dynamic: requires-dist
Dynamic: requires-python
Dynamic: summary
